django_service_rating_store-0.3.0.dist-info/DESCRIPTION.rst
django_service_rating_store-0.3.0.dist-info/METADATA
django_service_rating_store-0.3.0.dist-info/metadata.json
django_service_rating_store-0.3.0.dist-info/RECORD
django_service_rating_store-0.3.0.dist-info/top_level.txt
django_service_rating_store-0.3.0.dist-info/WHEEL
servicerating/__init__.py
servicerating/actions.py
servicerating/admin.py
servicerating/api.py
servicerating/models.py
servicerating/tests.py
servicerating/urls.py
servicerating/views.py
servicerating/migrations/0001_initial.py
servicerating/migrations/__init__.py
