Metadata-Version: 2.0
Name: django-service-rating-store
Version: 0.3.0
Summary: Django app that allows storage and visualisation of Service Rating data posted via REST API
Home-page: https://github.com/praekelt/django-service-rating-store
Author: Praekelt Foundation
Author-email: devops@praekeltfoundation.org
License: BSD
Platform: UNKNOWN
Classifier: Development Status :: 4 - Beta
Classifier: Intended Audience :: Developers
Classifier: License :: OSI Approved :: BSD License
Classifier: Operating System :: POSIX
Classifier: Programming Language :: Python
Classifier: Topic :: Software Development :: Libraries :: Python Modules
Classifier: Topic :: System :: Networking
Requires-Dist: Django
Requires-Dist: django-tastypie
Requires-Dist: South
